pmml_ui/__init__.py
pmml_ui/app.py
pmml_ui/auth/__init__.py
pmml_ui/auth/add_user.py
pmml_ui/auth/db.py
pmml_ui/auth/forms.py
pmml_ui/auth/models.py
pmml_ui/auth/views.py
pmml_ui/config.py
pmml_ui/mailing_lists/__init__.py
pmml_ui/mailing_lists/exceptions.py
pmml_ui/mailing_lists/forms.py
pmml_ui/mailing_lists/models.py
pmml_ui/mailing_lists/views.py
pmml_ui/templates/auth/login.html
pmml_ui/templates/base.html
pmml_ui/templates/mailing_lists/add_member.html
pmml_ui/templates/mailing_lists/detail.html
pmml_ui/templates/mailing_lists/list.html
pmml_ui/updater/__init__.py
pmml_ui/updater/client.py
pmml_ui/updater/exceptions.py
pmml_ui/updater/k8s.py
pmml_ui/updater/models.py
pmml_ui-0.1.6.dist-info/WHEEL
pmml_ui-0.1.6.dist-info/entry_points.txt
pmml_ui-0.1.6.dist-info/METADATA
pmml_ui-0.1.6.dist-info/RECORD
