Metadata-Version: 2.1
Name: pmml-ui
Version: 0.1.6
Summary: Web ui for pmml
Author: Michael Wilson
Author-email: mw@1wilson.org
Requires-Python: >=3.9
Classifier: Programming Language :: Python :: 3
Classifier: Programming Language :: Python :: 3.9
Classifier: Programming Language :: Python :: 3.10
Classifier: Programming Language :: Python :: 3.11
Requires-Dist: Flask (>=2.2.3,<3.0.0)
Requires-Dist: flask-wtf (>=1.1.1,<2.0.0)
Requires-Dist: kubernetes (>=26.1.0,<27.0.0)
Requires-Dist: werkzeug (>=2.2.3,<3.0.0)
Requires-Dist: wtforms[email] (>=3.0.1,<4.0.0)
